oft/__init__.py
oft/py.typed
oft-0.0.1.dist-info/WHEEL
oft-0.0.1.dist-info/METADATA
oft-0.0.1.dist-info/RECORD
