Metadata-Version: 2.1
Name: oft
Version: 0.0.1
Summary: Open-platform Financial Toolbox
Author-email: Flavio Veloso Soares <flaviovs@magnux.com>
